[
  {
    "categoria": "Esportes",
    "dificuldade": "facil",
    "pergunta": "Quantos jogadores cada time possui em campo no futebol?",
    "resposta": "11",
    "pontos": 1
  },
  {
    "categoria": "Esportes",
    "dificuldade": "facil",
    "pergunta": "Qual país venceu a Copa do Mundo de 2002?",
    "resposta": "Brasil",
    "pontos": 1
  },
  {
    "categoria": "Esportes",
    "dificuldade": "facil",
    "pergunta": "Qual jogador brasileiro é conhecido como Rei do Futebol?",
    "resposta": "Pelé",
    "pontos": 1
  },
  {
    "categoria": "Esportes",
    "dificuldade": "facil",
    "pergunta": "Qual seleção venceu a Copa do Mundo de 2022?",
    "resposta": "Argentina",
    "pontos": 1
  },
  {
    "categoria": "Esportes",
    "dificuldade": "facil",
    "pergunta": "Em qual esporte atua Neymar?",
    "resposta": "Futebol",
    "pontos": 1
  },
  {
    "categoria": "Esportes",
    "dificuldade": "facil",
    "pergunta": "Qual é o principal torneio de seleções do futebol mundial?",
    "resposta": "Copa do Mundo",
    "pontos": 1
  },
  {
    "categoria": "Esportes",
    "dificuldade": "facil",
    "pergunta": "Qual país sediou a Copa do Mundo de 2014?",
    "resposta": "Brasil",
    "pontos": 1
  },
  {
    "categoria": "Esportes",
    "dificuldade": "facil",
    "pergunta": "Quantos anéis existem no símbolo olímpico?",
    "resposta": "5",
    "pontos": 1
  },
  {
    "categoria": "Esportes",
    "dificuldade": "facil",
    "pergunta": "Qual seleção é conhecida como La Albiceleste?",
    "resposta": "Argentina",
    "pontos": 1
  },
  {
    "categoria": "Esportes",
    "dificuldade": "facil",
    "pergunta": "Qual jogador argentino conquistou a Copa do Mundo de 2022?",
    "resposta": "Lionel Messi",
    "pontos": 1
  },
  {
    "categoria": "Esportes",
    "dificuldade": "facil",
    "pergunta": "Qual país possui mais títulos de Copa do Mundo?",
    "resposta": "Brasil",
    "pontos": 1
  },
  {
    "categoria": "Esportes",
    "dificuldade": "facil",
    "pergunta": "Qual é a cor tradicional da camisa da Seleção Brasileira?",
    "resposta": "Amarela",
    "pontos": 1
  },
  {
    "categoria": "Esportes",
    "dificuldade": "facil",
    "pergunta": "Quem é conhecido como Fenômeno no futebol brasileiro?",
    "resposta": "Ronaldo",
    "pontos": 1
  },
  {
    "categoria": "Esportes",
    "dificuldade": "facil",
    "pergunta": "Qual esporte utiliza uma bola oval?",
    "resposta": "Rugby",
    "pontos": 1
  },
  {
    "categoria": "Esportes",
    "dificuldade": "facil",
    "pergunta": "Em qual esporte Rebeca Andrade se destacou?",
    "resposta": "Ginástica Artística",
    "pontos": 1
  },
  {
    "categoria": "Esportes",
    "dificuldade": "facil",
    "pergunta": "Qual país sediou os Jogos Olímpicos de 2016?",
    "resposta": "Brasil",
    "pontos": 1
  },
  {
    "categoria": "Esportes",
    "dificuldade": "facil",
    "pergunta": "Qual seleção venceu a Copa do Mundo de 2018?",
    "resposta": "França",
    "pontos": 1
  },
  {
    "categoria": "Esportes",
    "dificuldade": "facil",
    "pergunta": "Qual é o nome da entidade máxima do futebol mundial?",
    "resposta": "FIFA",
    "pontos": 1
  },
  {
    "categoria": "Esportes",
    "dificuldade": "facil",
    "pergunta": "Quantos tempos tem uma partida de futebol?",
    "resposta": "2",
    "pontos": 1
  },
  {
    "categoria": "Esportes",
    "dificuldade": "facil",
    "pergunta": "Quantos minutos tem cada tempo de uma partida oficial?",
    "resposta": "45",
    "pontos": 1
  },
  {
    "categoria": "Esportes",
    "dificuldade": "facil",
    "pergunta": "Qual atleta brasileiro é conhecido como Mão Santa?",
    "resposta": "Oscar Schmidt",
    "pontos": 1
  },
  {
    "categoria": "Esportes",
    "dificuldade": "facil",
    "pergunta": "Qual país venceu a primeira Copa do Mundo em 1930?",
    "resposta": "Uruguai",
    "pontos": 1
  },
  {
    "categoria": "Esportes",
    "dificuldade": "facil",
    "pergunta": "Qual é o nome do troféu entregue ao campeão da Copa do Mundo?",
    "resposta": "Taça FIFA",
    "pontos": 1
  },
  {
    "categoria": "Esportes",
    "dificuldade": "facil",
    "pergunta": "Qual país é famoso pelos All Blacks?",
    "resposta": "Nova Zelândia",
    "pontos": 1
  },
  {
    "categoria": "Esportes",
    "dificuldade": "facil",
    "pergunta": "Qual esporte pratica Rayssa Leal?",
    "resposta": "Skate",
    "pontos": 1
  },
  {
    "categoria": "Esportes",
    "dificuldade": "facil",
    "pergunta": "Qual jogador ficou conhecido como Bruxo no futebol brasileiro?",
    "resposta": "Ronaldinho Gaúcho",
    "pontos": 1
  },
  {
    "categoria": "Esportes",
    "dificuldade": "facil",
    "pergunta": "Qual seleção eliminou o Brasil por 7 a 1 em 2014?",
    "resposta": "Alemanha",
    "pontos": 1
  },
  {
    "categoria": "Esportes",
    "dificuldade": "facil",
    "pergunta": "Qual é o esporte de Michael Phelps?",
    "resposta": "Natação",
    "pontos": 1
  },
  {
    "categoria": "Esportes",
    "dificuldade": "facil",
    "pergunta": "Qual seleção é conhecida como Azzurra?",
    "resposta": "Itália",
    "pontos": 1
  },
  {
    "categoria": "Esportes",
    "dificuldade": "facil",
    "pergunta": "Qual país sediou as Olimpíadas de Tóquio 2020?",
    "resposta": "Japão",
    "pontos": 1
  },
  {
    "categoria": "Esportes",
    "dificuldade": "facil",
    "pergunta": "Qual esporte usa uma rede e uma bola amarela pequena?",
    "resposta": "Tênis",
    "pontos": 1
  },
  {
    "categoria": "Esportes",
    "dificuldade": "facil",
    "pergunta": "Quem é o maior artilheiro da história das Copas do Mundo?",
    "resposta": "Miroslav Klose",
    "pontos": 1
  },
  {
    "categoria": "Esportes",
    "dificuldade": "facil",
    "pergunta": "Qual país venceu a Copa América de 2021?",
    "resposta": "Argentina",
    "pontos": 1
  },
  {
    "categoria": "Esportes",
    "dificuldade": "facil",
    "pergunta": "Qual é o principal torneio de clubes da Europa?",
    "resposta": "Liga dos Campeões",
    "pontos": 1
  },
  {
    "categoria": "Esportes",
    "dificuldade": "facil",
    "pergunta": "Qual brasileiro ganhou ouro olímpico no surfe em 2024?",
    "resposta": "Gabriel Medina",
    "pontos": 1
  },
  {
    "categoria": "Esportes",
    "dificuldade": "facil",
    "pergunta": "Qual seleção é chamada de Canarinho?",
    "resposta": "Brasil",
    "pontos": 1
  },
  {
    "categoria": "Esportes",
    "dificuldade": "facil",
    "pergunta": "Qual jogador português é conhecido pela sigla CR7?",
    "resposta": "Cristiano Ronaldo",
    "pontos": 1
  },
  {
    "categoria": "Esportes",
    "dificuldade": "facil",
    "pergunta": "Qual é a cor do cartão que resulta em expulsão no futebol?",
    "resposta": "Vermelho",
    "pontos": 1
  },
  {
    "categoria": "Esportes",
    "dificuldade": "facil",
    "pergunta": "Qual é a cor do cartão de advertência no futebol?",
    "resposta": "Amarelo",
    "pontos": 1
  },
  {
    "categoria": "Esportes",
    "dificuldade": "facil",
    "pergunta": "Qual país venceu a Copa do Mundo de 1994?",
    "resposta": "Brasil",
    "pontos": 1
  },

  {
    "categoria": "Esportes",
    "dificuldade": "media",
    "pergunta": "Qual seleção venceu a Copa do Mundo de 2010?",
    "resposta": "Espanha",
    "pontos": 3
  },
  {
    "categoria": "Esportes",
    "dificuldade": "media",
    "pergunta": "Quem marcou o gol do título da Espanha na Copa de 2010?",
    "resposta": "Andres Iniesta",
    "pontos": 3
  },
  {
    "categoria": "Esportes",
    "dificuldade": "media",
    "pergunta": "Qual país sediou a Copa do Mundo de 2018?",
    "resposta": "Rússia",
    "pontos": 3
  },
  {
    "categoria": "Esportes",
    "dificuldade": "media",
    "pergunta": "Quem foi o artilheiro da Copa do Mundo de 2014?",
    "resposta": "James Rodriguez",
    "pontos": 3
  },
  {
    "categoria": "Esportes",
    "dificuldade": "media",
    "pergunta": "Qual seleção eliminou o Brasil na Copa do Mundo de 2022?",
    "resposta": "Croácia",
    "pontos": 3
  },
  {
    "categoria": "Esportes",
    "dificuldade": "media",
    "pergunta": "Qual clube revelou Lionel Messi profissionalmente?",
    "resposta": "Barcelona",
    "pontos": 3
  },
  {
    "categoria": "Esportes",
    "dificuldade": "media",
    "pergunta": "Qual clube revelou Cristiano Ronaldo profissionalmente?",
    "resposta": "Sporting",
    "pontos": 3
  },
  {
    "categoria": "Esportes",
    "dificuldade": "media",
    "pergunta": "Quem foi o técnico da Seleção Brasileira campeã em 2002?",
    "resposta": "Luiz Felipe Scolari",
    "pontos": 3
  },
  {
    "categoria": "Esportes",
    "dificuldade": "media",
    "pergunta": "Qual país venceu a Eurocopa de 2016?",
    "resposta": "Portugal",
    "pontos": 3
  },
  {
    "categoria": "Esportes",
    "dificuldade": "media",
    "pergunta": "Quem marcou o gol do título de Portugal na Euro 2016?",
    "resposta": "Eder",
    "pontos": 3
  },
  {
    "categoria": "Esportes",
    "dificuldade": "media",
    "pergunta": "Qual seleção venceu a Copa América de 2019?",
    "resposta": "Brasil",
    "pontos": 3
  },
  {
    "categoria": "Esportes",
    "dificuldade": "media",
    "pergunta": "Qual seleção venceu a Copa América de 2024?",
    "resposta": "Argentina",
    "pontos": 3
  },
  {
    "categoria": "Esportes",
    "dificuldade": "media",
    "pergunta": "Qual país sediou as Olimpíadas de Londres em 2012?",
    "resposta": "Reino Unido",
    "pontos": 3
  },
  {
    "categoria": "Esportes",
    "dificuldade": "media",
    "pergunta": "Quem foi o atleta mais medalhado da história das Olimpíadas?",
    "resposta": "Michael Phelps",
    "pontos": 3
  },
  {
    "categoria": "Esportes",
    "dificuldade": "media",
    "pergunta": "Em qual cidade aconteceram as Olimpíadas de 2008?",
    "resposta": "Pequim",
    "pontos": 3
  },
  {
    "categoria": "Esportes",
    "dificuldade": "media",
    "pergunta": "Qual brasileira conquistou ouro olímpico no salto sobre a mesa em 2024?",
    "resposta": "Rebeca Andrade",
    "pontos": 3
  },
  {
    "categoria": "Esportes",
    "dificuldade": "media",
    "pergunta": "Quem acendeu a pira olímpica na abertura do Rio 2016?",
    "resposta": "Vanderlei Cordeiro de Lima",
    "pontos": 3
  },
  {
    "categoria": "Esportes",
    "dificuldade": "media",
    "pergunta": "Qual jogador é conhecido como La Pulga?",
    "resposta": "Lionel Messi",
    "pontos": 3
  },
  {
    "categoria": "Esportes",
    "dificuldade": "media",
    "pergunta": "Qual goleiro brasileiro foi titular na conquista da Copa de 2002?",
    "resposta": "Marcos",
    "pontos": 3
  },
  {
    "categoria": "Esportes",
    "dificuldade": "media",
    "pergunta": "Qual seleção foi vice-campeã da Copa do Mundo de 2022?",
    "resposta": "França",
    "pontos": 3
  },
  {
    "categoria": "Esportes",
    "dificuldade": "media",
    "pergunta": "Quem foi o artilheiro da Copa do Mundo de 2022?",
    "resposta": "Kylian Mbappe",
    "pontos": 3
  },
  {
    "categoria": "Esportes",
    "dificuldade": "media",
    "pergunta": "Qual país venceu a Copa do Mundo de 2006?",
    "resposta": "Itália",
    "pontos": 3
  },
  {
    "categoria": "Esportes",
    "dificuldade": "media",
    "pergunta": "Contra qual seleção Zidane foi expulso na final da Copa de 2006?",
    "resposta": "Itália",
    "pontos": 3
  },
  {
    "categoria": "Esportes",
    "dificuldade": "media",
    "pergunta": "Qual clube é conhecido como Merengue?",
    "resposta": "Real Madrid",
    "pontos": 3
  },
  {
    "categoria": "Esportes",
    "dificuldade": "media",
    "pergunta": "Qual clube é conhecido como Blaugrana?",
    "resposta": "Barcelona",
    "pontos": 3
  },
  {
    "categoria": "Esportes",
    "dificuldade": "media",
    "pergunta": "Qual seleção venceu o ouro olímpico no futebol masculino em 2016?",
    "resposta": "Brasil",
    "pontos": 3
  },
  {
    "categoria": "Esportes",
    "dificuldade": "media",
    "pergunta": "Contra qual seleção o Brasil conquistou o ouro olímpico em 2016?",
    "resposta": "Alemanha",
    "pontos": 3
  },
  {
    "categoria": "Esportes",
    "dificuldade": "media",
    "pergunta": "Quem marcou o último pênalti do Brasil na final olímpica de 2016?",
    "resposta": "Neymar",
    "pontos": 3
  },
  {
    "categoria": "Esportes",
    "dificuldade": "media",
    "pergunta": "Qual atleta jamaicano ganhou oito medalhas de ouro olímpicas no atletismo?",
    "resposta": "Usain Bolt",
    "pontos": 3
  },
  {
    "categoria": "Esportes",
    "dificuldade": "media",
    "pergunta": "Qual atleta brasileira é conhecida como Fadinha?",
    "resposta": "Rayssa Leal",
    "pontos": 3
  },
  {
    "categoria": "Esportes",
    "dificuldade": "media",
    "pergunta": "Qual país venceu a primeira medalha de ouro do futebol olímpico masculino?",
    "resposta": "Grã Bretanha",
    "pontos": 3
  },
  {
    "categoria": "Esportes",
    "dificuldade": "media",
    "pergunta": "Qual seleção venceu a Copa das Confederações de 2013?",
    "resposta": "Brasil",
    "pontos": 3
  },
  {
    "categoria": "Esportes",
    "dificuldade": "media",
    "pergunta": "Quem foi eleito o melhor jogador da Copa do Mundo de 2014?",
    "resposta": "Lionel Messi",
    "pontos": 3
  },
  {
    "categoria": "Esportes",
    "dificuldade": "media",
    "pergunta": "Quem foi eleito o melhor jogador da Copa do Mundo de 2022?",
    "resposta": "Lionel Messi",
    "pontos": 3
  },
  {
    "categoria": "Esportes",
    "dificuldade": "media",
    "pergunta": "Qual seleção conquistou a Eurocopa de 2021?",
    "resposta": "Itália",
    "pontos": 3
  },
  {
    "categoria": "Esportes",
    "dificuldade": "media",
    "pergunta": "Qual país sediou a Eurocopa de 2024?",
    "resposta": "Alemanha",
    "pontos": 3
  },
  {
    "categoria": "Esportes",
    "dificuldade": "media",
    "pergunta": "Qual atleta brasileiro conquistou ouro olímpico no salto com vara em 2016?",
    "resposta": "Thiago Braz",
    "pontos": 3
  },
  {
    "categoria": "Esportes",
    "dificuldade": "media",
    "pergunta": "Qual seleção é conhecida como Oranje?",
    "resposta": "Holanda",
    "pontos": 3
  },
  {
    "categoria": "Esportes",
    "dificuldade": "media",
    "pergunta": "Qual seleção ficou famosa pela geração chamada de Carrossel Holandês?",
    "resposta": "Holanda",
    "pontos": 3
  },
  {
    "categoria": "Esportes",
    "dificuldade": "media",
    "pergunta": "Qual jogador brasileiro venceu a Bola de Ouro em 2007?",
    "resposta": "Kaka",
    "pontos": 3
  },

  {
    "categoria": "Esportes",
    "dificuldade": "dificil",
    "pergunta": "Quem foi o artilheiro da Copa do Mundo de 1998?",
    "resposta": "Davor Suker",
    "pontos": 5
  },
  {
    "categoria": "Esportes",
    "dificuldade": "dificil",
    "pergunta": "Qual seleção eliminou o Brasil na final da Copa do Mundo de 1998?",
    "resposta": "França",
    "pontos": 5
  },
  {
    "categoria": "Esportes",
    "dificuldade": "dificil",
    "pergunta": "Quem marcou os dois gols da França na final da Copa do Mundo de 1998?",
    "resposta": "Zinedine Zidane",
    "pontos": 5
  },
  {
    "categoria": "Esportes",
    "dificuldade": "dificil",
    "pergunta": "Qual seleção venceu a Copa do Mundo de 1978?",
    "resposta": "Argentina",
    "pontos": 5
  },
  {
    "categoria": "Esportes",
    "dificuldade": "dificil",
    "pergunta": "Quem foi o capitão da Seleção Brasileira na conquista da Copa de 1970?",
    "resposta": "Carlos Alberto Torres",
    "pontos": 5
  },
  {
    "categoria": "Esportes",
    "dificuldade": "dificil",
    "pergunta": "Qual jogador marcou o quarto gol do Brasil na final da Copa de 1970?",
    "resposta": "Carlos Alberto Torres",
    "pontos": 5
  },
  {
    "categoria": "Esportes",
    "dificuldade": "dificil",
    "pergunta": "Qual país sediou a primeira Copa do Mundo?",
    "resposta": "Uruguai",
    "pontos": 5
  },
  {
    "categoria": "Esportes",
    "dificuldade": "dificil",
    "pergunta": "Quem foi o técnico da Seleção Brasileira campeã da Copa do Mundo de 1994?",
    "resposta": "Carlos Alberto Parreira",
    "pontos": 5
  },
  {
    "categoria": "Esportes",
    "dificuldade": "dificil",
    "pergunta": "Qual seleção venceu a Copa do Mundo de 1954?",
    "resposta": "Alemanha Ocidental",
    "pontos": 5
  },
  {
    "categoria": "Esportes",
    "dificuldade": "dificil",
    "pergunta": "Quem ficou conhecido como Kaiser Franz no futebol?",
    "resposta": "Franz Beckenbauer",
    "pontos": 5
  },
  {
    "categoria": "Esportes",
    "dificuldade": "dificil",
    "pergunta": "Qual jogador ganhou a Bola de Ouro de 1999?",
    "resposta": "Rivaldo",
    "pontos": 5
  },
  {
    "categoria": "Esportes",
    "dificuldade": "dificil",
    "pergunta": "Qual clube venceu a primeira edição da Liga dos Campeões da UEFA?",
    "resposta": "Real Madrid",
    "pontos": 5
  },
  {
    "categoria": "Esportes",
    "dificuldade": "dificil",
    "pergunta": "Quem é o maior vencedor da Liga dos Campeões como jogador?",
    "resposta": "Francisco Gento",
    "pontos": 5
  },
  {
    "categoria": "Esportes",
    "dificuldade": "dificil",
    "pergunta": "Qual seleção venceu a Eurocopa de 2004 de forma surpreendente?",
    "resposta": "Grécia",
    "pontos": 5
  },
  {
    "categoria": "Esportes",
    "dificuldade": "dificil",
    "pergunta": "Quem marcou o gol do título da Grécia na Eurocopa de 2004?",
    "resposta": "Angelos Charisteas",
    "pontos": 5
  },
  {
    "categoria": "Esportes",
    "dificuldade": "dificil",
    "pergunta": "Qual jogador brasileiro ganhou a Bola de Ouro de 2005?",
    "resposta": "Ronaldinho Gaucho",
    "pontos": 5
  },
  {
    "categoria": "Esportes",
    "dificuldade": "dificil",
    "pergunta": "Qual país sediou os Jogos Olímpicos de 1936?",
    "resposta": "Alemanha",
    "pontos": 5
  },
  {
    "categoria": "Esportes",
    "dificuldade": "dificil",
    "pergunta": "Qual atleta conquistou quatro medalhas de ouro em Berlim 1936?",
    "resposta": "Jesse Owens",
    "pontos": 5
  },
  {
    "categoria": "Esportes",
    "dificuldade": "dificil",
    "pergunta": "Quem foi o primeiro atleta a correr os 100 metros abaixo de 10 segundos oficialmente?",
    "resposta": "Jim Hines",
    "pontos": 5
  },
  {
    "categoria": "Esportes",
    "dificuldade": "dificil",
    "pergunta": "Qual atleta brasileiro ficou famoso pelo ouro olímpico no salto triplo em 1984?",
    "resposta": "Joao do Pulo",
    "pontos": 5
  },
  {
    "categoria": "Esportes",
    "dificuldade": "dificil",
    "pergunta": "Qual país liderou o quadro de medalhas das Olimpíadas de Tóquio 2020?",
    "resposta": "Estados Unidos",
    "pontos": 5
  },
  {
    "categoria": "Esportes",
    "dificuldade": "dificil",
    "pergunta": "Qual nadador conquistou 23 medalhas de ouro olímpicas?",
    "resposta": "Michael Phelps",
    "pontos": 5
  },
  {
    "categoria": "Esportes",
    "dificuldade": "dificil",
    "pergunta": "Quem é o maior artilheiro da história da Seleção Brasileira masculina?",
    "resposta": "Neymar",
    "pontos": 5
  },
  {
    "categoria": "Esportes",
    "dificuldade": "dificil",
    "pergunta": "Qual jogador marcou o gol do título da Copa do Mundo de 2014?",
    "resposta": "Mario Gotze",
    "pontos": 5
  },
  {
    "categoria": "Esportes",
    "dificuldade": "dificil",
    "pergunta": "Qual seleção foi derrotada pela Alemanha na final da Copa de 2014?",
    "resposta": "Argentina",
    "pontos": 5
  },
  {
    "categoria": "Esportes",
    "dificuldade": "dificil",
    "pergunta": "Quem foi o capitão da Argentina campeã do mundo em 2022?",
    "resposta": "Lionel Messi",
    "pontos": 5
  },
  {
    "categoria": "Esportes",
    "dificuldade": "dificil",
    "pergunta": "Qual seleção venceu a primeira edição da Eurocopa em 1960?",
    "resposta": "Uniao Sovietica",
    "pontos": 5
  },
  {
    "categoria": "Esportes",
    "dificuldade": "dificil",
    "pergunta": "Quem foi o goleiro da Itália campeã da Copa do Mundo de 2006?",
    "resposta": "Gianluigi Buffon",
    "pontos": 5
  },
  {
    "categoria": "Esportes",
    "dificuldade": "dificil",
    "pergunta": "Qual país conquistou o ouro olímpico no futebol masculino em 1992?",
    "resposta": "Espanha",
    "pontos": 5
  },
  {
    "categoria": "Esportes",
    "dificuldade": "dificil",
    "pergunta": "Qual atleta brasileiro conquistou ouro olímpico na maratona em Atenas 2004 após sofrer uma agressão durante a prova?",
    "resposta": "Vanderlei Cordeiro de Lima",
    "pontos": 5
  },
  {
    "categoria": "Esportes",
    "dificuldade": "dificil",
    "pergunta": "Qual jogador venceu oito Bolas de Ouro até 2023?",
    "resposta": "Lionel Messi",
    "pontos": 5
  },
  {
    "categoria": "Esportes",
    "dificuldade": "dificil",
    "pergunta": "Qual clube português revelou Luis Figo?",
    "resposta": "Sporting",
    "pontos": 5
  },
  {
    "categoria": "Esportes",
    "dificuldade": "dificil",
    "pergunta": "Qual seleção venceu a Copa do Mundo de 1958?",
    "resposta": "Brasil",
    "pontos": 5
  },
  {
    "categoria": "Esportes",
    "dificuldade": "dificil",
    "pergunta": "Quem marcou dois gols para o Brasil na final da Copa de 1958?",
    "resposta": "Pele",
    "pontos": 5
  },
  {
    "categoria": "Esportes",
    "dificuldade": "dificil",
    "pergunta": "Qual atleta ficou conhecido como O Homem Mais Rapido do Mundo?",
    "resposta": "Usain Bolt",
    "pontos": 5
  },
  {
    "categoria": "Esportes",
    "dificuldade": "dificil",
    "pergunta": "Qual seleção conquistou a Copa do Mundo de 1986?",
    "resposta": "Argentina",
    "pontos": 5
  },
  {
    "categoria": "Esportes",
    "dificuldade": "dificil",
    "pergunta": "Quem marcou o famoso gol conhecido como A Mao de Deus?",
    "resposta": "Diego Maradona",
    "pontos": 5
  },
  {
    "categoria": "Esportes",
    "dificuldade": "dificil",
    "pergunta": "Qual país sediou os Jogos Olímpicos de Atenas em 2004?",
    "resposta": "Grecia",
    "pontos": 5
  },
  {
    "categoria": "Esportes",
    "dificuldade": "dificil",
    "pergunta": "Qual seleção venceu a Copa do Mundo de 1966?",
    "resposta": "Inglaterra",
    "pontos": 5
  },
  {
    "categoria": "Esportes",
    "dificuldade": "dificil",
    "pergunta": "Quem marcou o gol que garantiu o ouro olímpico do Brasil no futebol masculino em 2016 na disputa por pênaltis?",
    "resposta": "Neymar",
    "pontos": 5
  }
]